{
  "kind": "singleType",
  "collectionName": "gallery_areas",
  "info": {
    "name": "gallery_area"
  },
  "options": {
    "increments": true,
    "timestamps": true,
    "draftAndPublish": true
  },
  "attributes": {
    "content": {
      "type": "dynamiczone",
      "components": [
        "gallery-area.photos",
        "gallery-area.videos"
      ]
    },
    "title": {
      "type": "string"
    },
    "desc1": {
      "type": "text"
    },
    "desc2": {
      "type": "richtext"
    }
  }
}
